MANIFEST.in
README.md
setup.py
markdownserver/__init__.py
markdownserver/cli.py
markdownserver/handlers.py
markdownserver/indexer.py
markdownserver/markdown.py
markdownserver/master.mako
markdownserver.egg-info/PKG-INFO
markdownserver.egg-info/SOURCES.txt
markdownserver.egg-info/dependency_links.txt
markdownserver.egg-info/entry_points.txt
markdownserver.egg-info/requires.txt
markdownserver.egg-info/top_level.txt
markdownserver/static/bootstrap.min.css
markdownserver/static/style.css