Metadata-Version: 2.1
Name: markdownserver
Version: 1.0.18
Summary: markdown http server
Home-page: https://github.com/babakhani/markdownserver
Author: Reza Babakhani
Author-email: babakhani.reza@gmail.com
License: MIT
Platform: UNKNOWN
